LICENSE
nnviz/__init__.py
nnviz/dataspec.py
nnviz/entities.py
nnviz/cli/__init__.py
nnviz/cli/main.py
nnviz/colors/__init__.py
nnviz/colors/base.py
nnviz/colors/bubble.py
nnviz/colors/hashcolor.py
nnviz/drawing/__init__.py
nnviz/drawing/base.py
nnviz/drawing/graphviz.py
nnviz/inspection/__init__.py
nnviz/inspection/base.py
nnviz/inspection/torchfx.py
nnviz-1.0.0.dist-info/METADATA
nnviz-1.0.0.dist-info/WHEEL
nnviz-1.0.0.dist-info/entry_points.txt
nnviz-1.0.0.dist-info/licenses/LICENSE
nnviz-1.0.0.dist-info/RECORD
