Metadata-Version: 2.1
Name: nnviz
Version: 1.0.0
Summary: Neural models visualization.
Project-URL: Source, https://github.com/lucabonfiglioli/nnviz
Project-URL: Issues, https://github.com/lucabonfiglioli/nnviz/issues
Author-email: LucaBonfiglioli <luca.bonfiglioli@gmail.com>
License: GNU General Public License v3 (GPLv3)
License-File: LICENSE
Keywords: deeplearning,graph,neural,nnviz,visualization
Classifier: Development Status :: 3 - Alpha
Classifier: Intended Audience :: Developers
Classifier: Intended Audience :: Science/Research
Classifier: License :: OSI Approved :: GNU General Public License v3 (GPLv3)
Classifier: Natural Language :: English
Classifier: Operating System :: OS Independent
Classifier: Programming Language :: Python :: 3
Classifier: Programming Language :: Python :: 3.8
Classifier: Topic :: Scientific/Engineering
Classifier: Topic :: Software Development
Requires-Python: >=3.8
Requires-Dist: networkx>=2.8
Requires-Dist: numpy
Requires-Dist: pydantic>=1.10
Requires-Dist: pygraphviz>=1.9
Requires-Dist: torch>=1.12
Requires-Dist: torchvision>=0.13
Requires-Dist: typer>=0.6.0
Provides-Extra: build
Requires-Dist: build; extra == 'build'
Requires-Dist: hatch; extra == 'build'
Provides-Extra: dev
Requires-Dist: black; extra == 'dev'
Requires-Dist: flake8; extra == 'dev'
Requires-Dist: ruff; extra == 'dev'
Provides-Extra: docs
Requires-Dist: myst-parser==1.0.0; extra == 'docs'
Requires-Dist: sphinx-immaterial==0.11.3; extra == 'docs'
Requires-Dist: sphinx==6.1.3; extra == 'docs'
Requires-Dist: sphinxcontrib-mermaid==0.8.1; extra == 'docs'
Provides-Extra: tests
Requires-Dist: pytest; extra == 'tests'
Requires-Dist: pytest-cov; extra == 'tests'
